http_fetch_operator/__init__.py
http_fetch_operator/http_fetch_operator.py
amsterdam_airflow_http_fetch_operator-1.0.dist-info/WHEEL
amsterdam_airflow_http_fetch_operator-1.0.dist-info/METADATA
amsterdam_airflow_http_fetch_operator-1.0.dist-info/RECORD
